fastapi_derive_responses/__init__.py
fastapi_derive_responses-0.1.5.dist-info/LICENSE
fastapi_derive_responses-0.1.5.dist-info/METADATA
fastapi_derive_responses-0.1.5.dist-info/WHEEL
fastapi_derive_responses-0.1.5.dist-info/RECORD
