Metadata-Version: 2.3
Name: fastapi-derive-responses
Version: 0.1.5
Summary: FastAPI plugin to derive route responses based on source code.
License: MIT
Author: Ruslan Bel'kov
Author-email: ruslan.belckov@yandex.ru
Requires-Python: >=3.12,<4.0
Classifier: License :: OSI Approved :: MIT License
Classifier: Programming Language :: Python :: 3
Classifier: Programming Language :: Python :: 3.12
Classifier: Programming Language :: Python :: 3.13
Requires-Dist: pytest (>=8.3.4,<9.0.0)
Project-URL: Repository, https://github.com/dantetemplar/fastapi-derive-responses
